textsimi/__init__.py
textsimi/ts.py
textsimi/ts_model_based.py
textsimi/TfIdf/__init__.py
textsimi/TfIdf/_pipe.py
textsimi-0.4.2.dist-info/LICENSE
textsimi-0.4.2.dist-info/METADATA
textsimi-0.4.2.dist-info/WHEEL
textsimi-0.4.2.dist-info/top_level.txt
textsimi-0.4.2.dist-info/RECORD
