Metadata-Version: 2.1
Name: textsimi
Version: 0.4.2
Summary: A package for text similarity
Home-page: https://github.com/leoxiang66/texts_similarity
Author: Tao Xiang
Author-email: tao.xiang@tum.de
License: UNKNOWN
Platform: UNKNOWN
Classifier: Programming Language :: Python :: 3.8
Classifier: License :: OSI Approved :: MIT License
License-File: LICENSE
Requires-Dist: textdistance
Requires-Dist: numpy
Requires-Dist: torch
Requires-Dist: scikit-learn
Requires-Dist: sparse-dot-topn
Requires-Dist: pandas
